mars_mcd_helper/__init__.py
mars_mcd_helper/__main__.py
mars_mcd_helper/cli.py
mars_mcd_helper/convenience.py
mars_mcd_helper/get_mars_data.py
mars_mcd_helper/read_mars_data.py
mars_mcd_helper-0.1.2.dist-info/entry_points.txt
mars_mcd_helper-0.1.2.dist-info/LICENSE
mars_mcd_helper-0.1.2.dist-info/WHEEL
mars_mcd_helper-0.1.2.dist-info/METADATA
mars_mcd_helper-0.1.2.dist-info/RECORD
