Metadata-Version: 2.1
Name: mars-mcd-helper
Version: 0.1.2
Summary: Utilities for retrieving and processing data from the Mars Climate Database
Home-page: https://github.com/2e0byo/mars-mcd-helper
License: MIT
Author: John Morris
Author-email: john.morris@durham.ac.uk
Requires-Python: >=3.7,<3.11
Classifier: License :: OSI Approved :: MIT License
Classifier: Programming Language :: Python :: 3
Classifier: Programming Language :: Python :: 3.10
Classifier: Programming Language :: Python :: 3.7
Classifier: Programming Language :: Python :: 3.8
Classifier: Programming Language :: Python :: 3.9
Requires-Dist: beautifulsoup4 (>=4.9.3,<5.0.0)
Requires-Dist: numpy (>=1.21.2,<2.0.0)
Requires-Dist: requests (>=2.26.0,<3.0.0)
Project-URL: Repository, https://github.com/2e0byo/mars-mcd-helper
